cprior/__init__.py
cprior/_lib/__init__.py
cprior/_lib/_cprior.so
cprior/_lib/cprior.py
cprior/cdist/__init__.py
cprior/cdist/base.py
cprior/cdist/beta.py
cprior/cdist/ci.py
cprior/cdist/gamma.py
cprior/cdist/normal_inverse_gamma.py
cprior/cdist/pareto.py
cprior/cdist/utils.py
cprior/experiment/__init__.py
cprior/experiment/base.py
cprior/experiment/plotting.py
cprior/experiment/utils.py
cprior/models/__init__.py
cprior/models/bernoulli.py
cprior/models/binomial.py
cprior/models/exponential.py
cprior/models/geometric.py
cprior/models/lognormal.py
cprior/models/negative_binomial.py
cprior/models/normal.py
cprior/models/poisson.py
cprior/models/uniform.py
cprior-0.4.0.data/data/cprior/_lib/_cprior.so
cprior-0.4.0.dist-info/LICENSE
cprior-0.4.0.dist-info/METADATA
cprior-0.4.0.dist-info/WHEEL
cprior-0.4.0.dist-info/top_level.txt
cprior-0.4.0.dist-info/RECORD
