Metadata-Version: 2.1
Name: cprior
Version: 0.4.0
Summary: Fast Bayesian A/B and multivariate testing
Home-page: https://github.com/guillermo-navas-palencia/cprior
Author: Guillermo Navas-Palencia
Author-email: g.navas.palencia@gmail.com
License: LGPL
Platform: any
Classifier: Topic :: Scientific/Engineering :: Mathematics
Classifier: License :: OSI Approved :: GNU General Public License v3 (GPLv3)
Classifier: Programming Language :: Python :: 3
Classifier: Programming Language :: Python :: 3.5
Classifier: Programming Language :: Python :: 3.6
Classifier: Programming Language :: Python :: 3.7
Requires-Python: >=3.5
